setup.cfg
setup.py
docker_link_helper.egg-info/PKG-INFO
docker_link_helper.egg-info/SOURCES.txt
docker_link_helper.egg-info/dependency_links.txt
docker_link_helper.egg-info/entry_points.txt
docker_link_helper.egg-info/top_level.txt
helper/__init__.py