Metadata-Version: 1.1
Name: docker-link-helper
Version: 0.0.2
Summary: Search for occurrences of docker links and replace them by their value
Home-page: https://github.com/tback/docker-link-helper
Author: Till Backhaus
Author-email: till@backha.us
License: MIT
Download-URL: https://github.com/tback/docker-link-helper/tarball/0.0.2
Keywords: docker,environment-variable,docker link
Platform: UNKNOWN
